MANIFEST.in
RELEASE-VERSION
setup.py
version.py
fose/__init__.py
fose/compliance.py
fose/protocol.py
fose/tests.py
fose/thread.xsd
fose/user.xsd
fose.egg-info/PKG-INFO
fose.egg-info/SOURCES.txt
fose.egg-info/dependency_links.txt
fose.egg-info/entry_points.txt
fose.egg-info/requires.txt
fose.egg-info/top_level.txt
fose/models/Thread.py
fose/models/__init__.py