Metadata-Version: 1.0
Name: fose
Version: 0.0.post23
Summary: Framework for Open Science Evaluation Core Package
Home-page: https://github.com/ilogue/fose
Author: Jasper van den Bosch
Author-email: jasper.jf.vandenbosch@gmail.com
License: UNKNOWN
Platform: UNKNOWN
